missionctl/__init__.py
missionctl/cli.py
missionctl-0.0.1.dist-info/METADATA
missionctl-0.0.1.dist-info/WHEEL
missionctl-0.0.1.dist-info/entry_points.txt
missionctl-0.0.1.dist-info/top_level.txt
missionctl-0.0.1.dist-info/RECORD
