Metadata-Version: 2.4
Name: missionctl
Version: 0.0.1
Summary: Example Python Package
Author: Ryan Petrello
Author-email: rpetrello@missioncloud.com
Requires-Python: >=3.6
